<?xml version="1.0" encoding="UTF-8"?>
<beans xmlns="http://www.springframework.org/schema/beans"
	xmlns:xsi="http://www.w3.org/2001/XMLSchema-instance"
	xsi:schemaLocation="http://www.springframework.org/schema/beans 
						http://www.springframework.org/schema/beans/spring-beans.xsd">
						
		<!-- DB Connection  -->
		<!--  DataSource -->
		<bean id="dataSource" class="org.springframework.jndi.JndiObjectFactoryBean">
			<property name="jndiName" value="java:/comp/env/jdbc/XE" />
		</bean>
		
		<!-- Mybatis Sqlsession  -->	
		<bean id="sqlSessionFactory" class="org.mybatis.spring.SqlSessionFactoryBean">
			<property name="dataSource" ref="dataSource" />
			<property name="configLocation" value="classpath:/mybatisConfig/mybatis-config.xml" />
			<property name="mapperLocations" value="classpath:/mybatisQuery/*.xml" />
		</bean>

		<bean id="sqlSession" class="org.mybatis.spring.SqlSessionTemplate"
			destroy-method="clearCache">
			<constructor-arg name="sqlSessionFactory" ref="sqlSessionFactory" />	
		</bean>

		<bean id="transactionManager" 
				class="org.springframework.jdbc.datasource.DataSourceTransactionManager">
				<property name="dataSource" ref="dataSource" />
				
		</bean>
		
		<bean class="org.mybatis.spring.mapper.MapperScannerConfigurer">
			<property name="basePackage"> 
				<value>com.jns.**.dao</value>	
			</property>	
		</bean>
</beans>